{
  "code": 0,
  "message": "Success",
  "zpData": {
    "resCount": 450,
    "filterString": "",
    "lid": "954vhY6j6aJ",
    "hasMore": true,
    "jobList": [
      {
        "securityId": "6S5tqSFblBrA4-J1DmeBHEifXZe1Twbd2qqBpgKUwwPS5HCD7xiErCeCrziG0BZTR6CDg0ZnXtbCNBP0ApGgDgLaHX2ewkeILBeSuu-xj5LSVA7ptmc~",
        "bossAvatar": "https://img.bosszhipin.com/boss/avatar/avatar_7.png",
        "bossCert": 3,
        "encryptBossId": "d83c7ab46fe7b20e1HZy096-FVU~",
        "bossName": "蒋先生",
        "bossTitle": "人事",
        "goldHunter": 0,
        "bossOnline": false,
        "encryptJobId": "7273bc9da1a89b061nB83Nm5ElNX",
        "expectId": 0,
        "jobName": "数据统计员",
        "lid": "954vhY6j6aJ.search.151",
        "salaryDesc": "6-10K·13薪",
        "jobLabels": [
          "1年以内",
          "大专"
        ],
        "jobValidStatus": 1,
        "iconWord": "",
        "skills": [
          "Python"
        ],
        "jobExperience": "1年以内",
        "daysPerWeekDesc": "",
        "leastMonthDesc": "",
        "jobDegree": "大专",
        "cityName": "唐山",
        "areaDistrict": "遵化市",
        "businessDistrict": "遵化市中心城区",
        "jobType": 0,
        "proxyJob": 0,
        "proxyType": 0,
        "anonymous": 0,
        "outland": 0,
        "optimal": 0,
        "iconFlagList": [],
        "itemId": 151,
        "city": 101090500,
        "isShield": 0,
        "atsDirectPost": false,
        "gps": null,
        "encryptBrandId": "acf1787a415b5af31nB52tW8EFU~",
        "brandName": "土木东方",
        "brandLogo": "https://img.bosszhipin.com/beijin/app/mobile/normal-0e3f1e4441a21d4874cece3a3d81f0fe.png",
        "brandStageName": "",
        "brandIndustry": "工程施工",
        "brandScaleName": "20-99人",
        "welfareList": [],
        "industry": 100702,
        "contact": false,
        "showTopPosition": false
      },
      {
        "securityId": "EjcxfNFBMBJ8M-e1RuDxyHZbfYHUSouvDMNmAdvJ5nO5SpXnh_dPJLId2sLfekmWETQUqqcBOt4etebCtIe8VbSrLCOp1Fa8RHxIU1E3qCCyg_TCKjE~",
        "bossAvatar": "https://img.bosszhipin.com/beijin/upload/avatar/20240118/607f1f3d68754fd03df82e449ac1627d0b3c75a235f5e95c091ba447f7824832f5ef1e84984a5b94_s.jpg.webp",
        "bossCert": 3,
        "encryptBossId": "311db82b063a512d33R93t-4ElU~",
        "bossName": "杨女士",
        "bossTitle": "Hr",
        "goldHunter": 0,
        "bossOnline": false,
        "encryptJobId": "045ec124739b8caf1HJ-0tS8FVNQ",
        "expectId": 0,
        "jobName": "物资主数据质量管理",
        "lid": "954vhY6j6aJ.search.152",
        "salaryDesc": "5-6K",
        "jobLabels": [
          "经验不限",
          "本科"
        ],
        "jobValidStatus": 1,
        "iconWord": "",
        "skills": [
          "数学/统计相关专业",
          "计算机相关专业",
          "数据分析/挖掘经验"
        ],
        "jobExperience": "经验不限",
        "daysPerWeekDesc": "",
        "leastMonthDesc": "",
        "jobDegree": "本科",
        "cityName": "北京",
        "areaDistrict": "东城区",
        "businessDistrict": "交道口",
        "jobType": 0,
        "proxyJob": 0,
        "proxyType": 0,
        "anonymous": 0,
        "outland": 0,
        "optimal": 0,
        "iconFlagList": [],
        "itemId": 152,
        "city": 101010100,
        "isShield": 0,
        "atsDirectPost": false,
        "gps": null,
        "encryptBrandId": "5c1d161fcf14b0871n143926FlI~",
        "brandName": "北方汉王",
        "brandLogo": "https://img.bosszhipin.com/beijin/icon/894ce6fa7e58d64d57e7f22d2f3a9d18afa7fcceaa24b8ea28f56f1bb14732c0.png",
        "brandStageName": "",
        "brandIndustry": "互联网",
        "brandScaleName": "100-499人",
        "welfareList": [
          "免费咖啡",
          "节日福利",
          "免费停车",
          "五险一金",
          "通讯补贴",
          "餐补",
          "加班补助",
          "包吃"
        ],
        "industry": 100020,
        "contact": false,
        "showTopPosition": false
      },
      {
        "securityId": "DESGYyPrvnlv3-d1S0jU08rXzZuq1kmBV-7cqQcxX8gKhFfUfzXDkDxoU9W4bBz9kEypTiImxalJUJJQyEmR4uDkEaQV3n14J0af7bxBXuI83x0CDSc~",
        "bossAvatar": "https://img.bosszhipin.com/beijin/upload/avatar/20221023/607f1f3d68754fd067f230b368e83b44d4c26c91d54f4357bf52c57acb2121c6a5baefbacc099b1b_s.png",
        "bossCert": 3,
        "encryptBossId": "cdde99551d7f49060nFz3dm_F1NU",
        "bossName": "朱先生",
        "bossTitle": "招聘者",
        "goldHunter": 0,
        "bossOnline": false,
        "encryptJobId": "7b093aeb320500321XF42NW9GVFU",
        "expectId": 0,
        "jobName": "数据专员",
        "lid": "954vhY6j6aJ.search.153",
        "salaryDesc": "6-10K",
        "jobLabels": [
          "经验不限",
          "本科"
        ],
        "jobValidStatus": 1,
        "iconWord": "",
        "skills": [
          "电商/零售行业数据相关经验",
          "文娱/游戏行业数据相关经验"
        ],
        "jobExperience": "经验不限",
        "daysPerWeekDesc": "",
        "leastMonthDesc": "",
        "jobDegree": "本科",
        "cityName": "长沙",
        "areaDistrict": "芙蓉区",
        "businessDistrict": "定王台",
        "jobType": 0,
        "proxyJob": 0,
        "proxyType": 0,
        "anonymous": 0,
        "outland": 0,
        "optimal": 0,
        "iconFlagList": [],
        "itemId": 153,
        "city": 101250100,
        "isShield": 0,
        "atsDirectPost": false,
        "gps": null,
        "encryptBrandId": "dc4da365b0b9fda31nZ62dy8GQ~~",
        "brandName": "阿斯嘉特",
        "brandLogo": "https://img.bosszhipin.com/beijin/mcs/chatphoto/20171115/09f576bf8fe2cfbdcc0834828254d3b32ee98815b0e01cc2fada17add3e09ddf.jpg",
        "brandStageName": "未融资",
        "brandIndustry": "音乐/视频/阅读",
        "brandScaleName": "100-499人",
        "welfareList": [
          "包吃"
        ],
        "industry": 100011,
        "contact": false,
        "showTopPosition": false
      },
      {
        "securityId": "JcrCsKZV6AxqA-b1a5uhjED6P14qFgBQT3EE6hLxu7z3Ji7lUUaOgWlci2WHyseE8wjGbW5ZkCUEpm1qM3BHs-RD2oGkdQM9I9uPEybpvsiqkNX95nc~",
        "bossAvatar": "https://img.bosszhipin.com/beijin/upload/avatar/20240616/607f1f3d68754fd01d1b9906c4a752cbedddcc6a3e131cb1209eb3d11a02ad64fd36f3b514657b51_s.png.webp",
        "bossCert": 3,
        "encryptBossId": "c4935502363a4e4b0nZ52d--GFRR",
        "bossName": "唐女士",
        "bossTitle": "HRD",
        "goldHunter": 0,
        "bossOnline": false,
        "encryptJobId": "2263ed4a2da9f7951HZy3di0F1dX",
        "expectId": 0,
        "jobName": "数据运营",
        "lid": "954vhY6j6aJ.search.154",
        "salaryDesc": "6-9K",
        "jobLabels": [
          "1-3年",
          "本科"
        ],
        "jobValidStatus": 1,
        "iconWord": "",
        "skills": [
          "经济/工商管理相关专业",
          "数学/统计相关专业",
          "分析报告"
        ],
        "jobExperience": "1-3年",
        "daysPerWeekDesc": "",
        "leastMonthDesc": "",
        "jobDegree": "本科",
        "cityName": "深圳",
        "areaDistrict": "龙岗区",
        "businessDistrict": "横岗",
        "jobType": 0,
        "proxyJob": 0,
        "proxyType": 0,
        "anonymous": 0,
        "outland": 0,
        "optimal": 0,
        "iconFlagList": [],
        "itemId": 154,
        "city": 101280600,
        "isShield": 0,
        "atsDirectPost": false,
        "gps": null,
        "encryptBrandId": "6a3831e3f4e8aeec1nd83N-1Fw~~",
        "brandName": "前海数据",
        "brandLogo": "https://img.bosszhipin.com/beijin/mcs/chatphoto/20180214/c9d34dbbff8d8db8ea7faa7e13427ddecfcd208495d565ef66e7dff9f98764da.jpg",
        "brandStageName": "未融资",
        "brandIndustry": "大数据",
        "brandScaleName": "100-499人",
        "welfareList": [
          "五险一金",
          "定期体检",
          "法定节假日三薪",
          "股票期权",
          "带薪年假",
          "零食下午茶",
          "节日福利",
          "全勤奖",
          "补充医疗保险",
          "生日福利",
          "项目奖金"
        ],
        "industry": 100005,
        "contact": false,
        "showTopPosition": false
      },
      {
        "securityId": "EDlxFTziJ0Gdg-w1Ip_syzycRLmQhFSCPgE5XLovMUZrwujFFdmwrwyDVlSDdefwz9t5_QSTxxtWCSGcAzwnYn0wRrk-Trty638f8qFkYaSc-hgQoRs~",
        "bossAvatar": "https://img.bosszhipin.com/boss/avatar/avatar_15.png",
        "bossCert": 3,
        "encryptBossId": "25addce157fa902e0XFz3d68GVo~",
        "bossName": "董先生",
        "bossTitle": "招聘主管",
        "goldHunter": 0,
        "bossOnline": false,
        "encryptJobId": "2bd338f870884a251Hdy0tq8GFVQ",
        "expectId": 0,
        "jobName": "数据工程师",
        "lid": "954vhY6j6aJ.search.155",
        "salaryDesc": "6-10K",
        "jobLabels": [
          "经验不限",
          "本科"
        ],
        "jobValidStatus": 1,
        "iconWord": "",
        "skills": [],
        "jobExperience": "经验不限",
        "daysPerWeekDesc": "",
        "leastMonthDesc": "",
        "jobDegree": "本科",
        "cityName": "长春",
        "areaDistrict": "南关区",
        "businessDistrict": "净月开发区",
        "jobType": 0,
        "proxyJob": 0,
        "proxyType": 0,
        "anonymous": 0,
        "outland": 0,
        "optimal": 0,
        "iconFlagList": [],
        "itemId": 155,
        "city": 101060100,
        "isShield": 0,
        "atsDirectPost": false,
        "gps": null,
        "encryptBrandId": "ce1aa0bab60054751Hd72tS1GFM~",
        "brandName": "吉林数字工坊",
        "brandLogo": "https://img.bosszhipin.com/beijin/icon/894ce6fa7e58d64d57e7f22d2f3a9d18afa7fcceaa24b8ea28f56f1bb14732c0.png",
        "brandStageName": "",
        "brandIndustry": "大数据",
        "brandScaleName": "20-99人",
        "welfareList": [],
        "industry": 100005,
        "contact": false,
        "showTopPosition": false
      },
      {
        "securityId": "0goRCWahV3YZ8-71PwynF-nWuIJtCrRCYcBvuRI-2rnJ4Ueixvj2x_jxzJF9l8Mlxwzf8ZojhTwUEY4RF21JwTUVDJuG1J-Tg97kizR7FKoVaFB7B9Zn4K_A6UCEZmLDZNPqtwWK6fWMbtjKaQl8",
        "bossAvatar": "https://img.bosszhipin.com/boss/avatar/avatar_9.png",
        "bossCert": 3,
        "encryptBossId": "6718decf5896ec3f0nR439i6GFA~",
        "bossName": "张女士",
        "bossTitle": "人事",
        "goldHunter": 0,
        "bossOnline": true,
        "encryptJobId": "13ea0e5d9a01bab91HB_3N-4F1BY",
        "expectId": 0,
        "jobName": "数据主管",
        "lid": "954vhY6j6aJ.search.156",
        "salaryDesc": "5-8K",
        "jobLabels": [
          "1-3年",
          "大专"
        ],
        "jobValidStatus": 1,
        "iconWord": "",
        "skills": [
          "SQL",
          "R",
          "Python"
        ],
        "jobExperience": "1-3年",
        "daysPerWeekDesc": "",
        "leastMonthDesc": "",
        "jobDegree": "大专",
        "cityName": "哈尔滨",
        "areaDistrict": "南岗区",
        "businessDistrict": "学府",
        "jobType": 0,
        "proxyJob": 0,
        "proxyType": 0,
        "anonymous": 0,
        "outland": 0,
        "optimal": 0,
        "iconFlagList": [],
        "itemId": 156,
        "city": 101050100,
        "isShield": 0,
        "atsDirectPost": false,
        "gps": null,
        "encryptBrandId": "43f7b583bf1a9e591X1z3t2_",
        "brandName": "新天地超市",
        "brandLogo": "https://img.bosszhipin.com/beijin/upload/com/workfeel/20211023/7bf6f160950405e9030b8946393f4197c09206aec63dc95973a79a2b2fe0059fe5a899d72c4b0fd3.jpg",
        "brandStageName": "未融资",
        "brandIndustry": "进出口贸易",
        "brandScaleName": "1000-9999人",
        "welfareList": [
          "免费班车",
          "包吃",
          "五险一金",
          "年终奖",
          "员工旅游",
          "全勤奖",
          "节日福利",
          "交通补助"
        ],
        "industry": 100504,
        "contact": false,
        "showTopPosition": false
      },
      {
        "securityId": "A03Bfy72JxvLG-H1SSZrtWttAUwU9Z6Nv-We_gTAG3BqzymAB9E1FtF14pDtFoOSocJFwCQEqoYOO4Gh-8o1XYeuRPKQZb00VK80NciCxynR_KSzCIyJv1SXSGM3kgI1VPW7mbOibyAgOQBcIwiYcv4~",
        "bossAvatar": "https://img.bosszhipin.com/beijin/upload/avatar/20240612/607f1f3d68754fd07f9f313921e60d102696d5e983919b1a4e50b0dd8893680e0ce6bd4343b1767a_s.png.webp",
        "bossCert": 3,
        "encryptBossId": "7d093cbbf629874803N43di9GFU~",
        "bossName": "吴先生",
        "bossTitle": "招聘HR",
        "goldHunter": 0,
        "bossOnline": true,
        "encryptJobId": "8efc6892221a7f4d1XN62961EFdQ",
        "expectId": 0,
        "jobName": "数据专员",
        "lid": "954vhY6j6aJ.search.157",
        "salaryDesc": "5-7K·13薪",
        "jobLabels": [
          "1-3年",
          "大专"
        ],
        "jobValidStatus": 1,
        "iconWord": "",
        "skills": [
          "业务数据分析",
          "数据分析/商业分析经验",
          "统计/数学相关专业"
        ],
        "jobExperience": "1-3年",
        "daysPerWeekDesc": "",
        "leastMonthDesc": "",
        "jobDegree": "大专",
        "cityName": "苏州",
        "areaDistrict": "常熟市",
        "businessDistrict": "尚湖风景区",
        "jobType": 0,
        "proxyJob": 0,
        "proxyType": 0,
        "anonymous": 0,
        "outland": 0,
        "optimal": 0,
        "iconFlagList": [],
        "itemId": 157,
        "city": 101190400,
        "isShield": 0,
        "atsDirectPost": false,
        "gps": null,
        "encryptBrandId": "c79fd57029fd86e21n1509m8ElA~",
        "brandName": "江苏中和动能科技",
        "brandLogo": "https://img.bosszhipin.com/beijin/upload/com/workfeel/20230527/7bf6f160950405e95cc465c62a15232df742327535a37f61a8876c468c129fd72c50210891d1dd90.jpg",
        "brandStageName": "未融资",
        "brandIndustry": "批发/零售",
        "brandScaleName": "1000-9999人",
        "welfareList": [],
        "industry": 100503,
        "contact": false,
        "showTopPosition": false
      },
      {
        "securityId": "mRIcpMpdd9nGx-81zbdHFOJmX76AToLhi8wPxvYE2x88ulNpdBWXuc39OhPkPfU7dA8duG9nUFqM3TU2YeM1ZFzvfyEAMqqZXTh8HfOuj0AozQC5",
        "bossAvatar": "https://img.bosszhipin.com/beijin/upload/avatar/20201115/94e656079f9b8d6b502c547b89d5fab184e131f166e47a354b55885a62d590e9_s.jpg",
        "bossCert": 3,
        "encryptBossId": "89226554cbc204991nd72N67F1E~",
        "bossName": "董女士",
        "bossTitle": "人力助理",
        "goldHunter": 0,
        "bossOnline": false,
        "encryptJobId": "cac971475869bea21n1y2Nq7FVFQ",
        "expectId": 0,
        "jobName": "数据处理专员",
        "lid": "954vhY6j6aJ.search.158",
        "salaryDesc": "6-10K·13薪",
        "jobLabels": [
          "1-3年",
          "大专"
        ],
        "jobValidStatus": 1,
        "iconWord": "",
        "skills": [
          "Excel",
          "SPSS",
          "细心",
          "耐心"
        ],
        "jobExperience": "1-3年",
        "daysPerWeekDesc": "",
        "leastMonthDesc": "",
        "jobDegree": "大专",
        "cityName": "北京",
        "areaDistrict": "海淀区",
        "businessDistrict": "西三旗",
        "jobType": 0,
        "proxyJob": 0,
        "proxyType": 0,
        "anonymous": 0,
        "outland": 0,
        "optimal": 0,
        "iconFlagList": [],
        "itemId": 158,
        "city": 101010100,
        "isShield": 0,
        "atsDirectPost": false,
        "gps": null,
        "encryptBrandId": "03140bc40a27204c1nJy2d26",
        "brandName": "北京博创联动",
        "brandLogo": "https://img.bosszhipin.com/beijin/mcs/chatphoto/20160518/70b120d87d55959c267fcf65cb61382c0a93c491bdcb279723e43cf80b460c3b.jpg",
        "brandStageName": "B轮",
        "brandIndustry": "大数据",
        "brandScaleName": "100-499人",
        "welfareList": [
          "年终奖",
          "五险一金",
          "餐补",
          "带薪年假"
        ],
        "industry": 100005,
        "contact": false,
        "showTopPosition": false
      },
      {
        "securityId": "oVbwWeixwnXSA-41MhAXkiEGqSr0ox7x3FGXphDOOMewtyLAvc_z0ze8OSyygAU4frYcemTNQKMs249FCBRuSceq6WJWaP0LqdHaq16_PLm-GUTTPZw~",
        "bossAvatar": "https://img.bosszhipin.com/boss/avatar/avatar_7.png",
        "bossCert": 3,
        "encryptBossId": "a05f421807157b8233Rz2dm-GVo~",
        "bossName": "严先生",
        "bossTitle": "HR",
        "goldHunter": 0,
        "bossOnline": false,
        "encryptJobId": "859f340cdee94f8e1HZy39q0ElRQ",
        "expectId": 0,
        "jobName": "数据中心主任",
        "lid": "954vhY6j6aJ.search.159",
        "salaryDesc": "6-10K",
        "jobLabels": [
          "1-3年",
          "本科"
        ],
        "jobValidStatus": 1,
        "iconWord": "",
        "skills": [
          "数学/统计相关专业",
          "数据分析/挖掘经验"
        ],
        "jobExperience": "1-3年",
        "daysPerWeekDesc": "",
        "leastMonthDesc": "",
        "jobDegree": "本科",
        "cityName": "亳州",
        "areaDistrict": "利辛县",
        "businessDistrict": "向阳路",
        "jobType": 0,
        "proxyJob": 0,
        "proxyType": 0,
        "anonymous": 0,
        "outland": 0,
        "optimal": 0,
        "iconFlagList": [],
        "itemId": 159,
        "city": 101220900,
        "isShield": 0,
        "atsDirectPost": false,
        "gps": null,
        "encryptBrandId": "259cd18e6d39b4ca1nV-2N-6FlY~",
        "brandName": "安徽浩翔农牧有限公司",
        "brandLogo": "https://c-res.zhipin.com/jrs/6_b1d4f5293948df381f5beded42001a0a.jpg",
        "brandStageName": "未融资",
        "brandIndustry": "农/林/牧/渔",
        "brandScaleName": "100-499人",
        "welfareList": [
          "带薪年假",
          "包住",
          "生日福利",
          "绩效奖金",
          "节日福利",
          "五险一金",
          "意外险",
          "有无线网",
          "工龄奖",
          "宿舍有空调",
          "交通补助",
          "包吃",
          "团建聚餐"
        ],
        "industry": 101303,
        "contact": false,
        "showTopPosition": false
      },
      {
        "securityId": "CfG2jQq7YpDKg-G1FOcijNyWBfOfRGapChAuyAVCo1Tah6qD2zghjFXtnHrjQJwxMdKp2BLBvBfmsDTEvvNdnfe1H9PLX7lkpNeEKpbEtrbdsMxcSnc~",
        "bossAvatar": "https://img.bosszhipin.com/beijin/upload/tmp/20201016/92292147be545e4e9f4dce08b6ae1ffbff1f5de794bbfbedf17cd3210997d21d_s.jpg",
        "bossCert": 3,
        "encryptBossId": "98a991e7012872690HR43N-7GFE~",
        "bossName": "蒋先生",
        "bossTitle": "招聘主管",
        "goldHunter": 0,
        "bossOnline": false,
        "encryptJobId": "f6f5ea6ce0ca359d1HN42t-5ElZX",
        "expectId": 0,
        "jobName": "统计数据专员",
        "lid": "954vhY6j6aJ.search.160",
        "salaryDesc": "6-8K",
        "jobLabels": [
          "1-3年",
          "大专"
        ],
        "jobValidStatus": 1,
        "iconWord": "",
        "skills": [
          "SQL",
          "计算机相关专业",
          "数学/统计相关专业",
          "数据分析/挖掘经验"
        ],
        "jobExperience": "1-3年",
        "daysPerWeekDesc": "",
        "leastMonthDesc": "",
        "jobDegree": "大专",
        "cityName": "杭州",
        "areaDistrict": "余杭区",
        "businessDistrict": "仁和",
        "jobType": 0,
        "proxyJob": 0,
        "proxyType": 0,
        "anonymous": 0,
        "outland": 0,
        "optimal": 0,
        "iconFlagList": [],
        "itemId": 160,
        "city": 101210100,
        "isShield": 0,
        "atsDirectPost": false,
        "gps": null,
        "encryptBrandId": "212b6b2c966e76271HF82d-1EVo~",
        "brandName": "浙江色香味食品开发",
        "brandLogo": "https://img.bosszhipin.com/beijin/icon/894ce6fa7e58d64d57e7f22d2f3a9d18afa7fcceaa24b8ea28f56f1bb14732c0.png",
        "brandStageName": "未融资",
        "brandIndustry": "新零售",
        "brandScaleName": "100-499人",
        "welfareList": [],
        "industry": 100017,
        "contact": false,
        "showTopPosition": false
      },
      {
        "securityId": "px_OOBRfdb3gp-n1_ENRFmqsYhRs7JU_nvnuJCQpH_sh92PiVlPdOZjPyISn8HNFIkjXfGSJPSZwjz0FX_1BH9Ma4hgkOx2s-yxxe6L4MwfBoEUY",
        "bossAvatar": "https://img.bosszhipin.com/beijin/upload/avatar/20221205/607f1f3d68754fd00218885bd0424d7088c772e740560b5552e814389fa5da52555083a866599c4d_s.jpg",
        "bossCert": 3,
        "encryptBossId": "ec54cc4d604b14050ndz3tu8EVI~",
        "bossName": "徐女士",
        "bossTitle": "高级经理",
        "goldHunter": 0,
        "bossOnline": false,
        "encryptJobId": "2ad225e55129c5d403J629W-EFY~",
        "expectId": 0,
        "jobName": "数据统计师",
        "lid": "954vhY6j6aJ.search.161",
        "salaryDesc": "6-11K",
        "jobLabels": [
          "1-3年",
          "本科"
        ],
        "jobValidStatus": 1,
        "iconWord": "",
        "skills": [
          "统计"
        ],
        "jobExperience": "1-3年",
        "daysPerWeekDesc": "",
        "leastMonthDesc": "",
        "jobDegree": "本科",
        "cityName": "嘉兴",
        "areaDistrict": "南湖区",
        "businessDistrict": "东栅",
        "jobType": 0,
        "proxyJob": 0,
        "proxyType": 0,
        "anonymous": 0,
        "outland": 0,
        "optimal": 0,
        "iconFlagList": [],
        "itemId": 161,
        "city": 101210300,
        "isShield": 0,
        "atsDirectPost": false,
        "gps": null,
        "encryptBrandId": "b8fe11a1f37172a71HF43tW0GA~~",
        "brandName": "德达医药",
        "brandLogo": "https://img.bosszhipin.com/beijin/upload/com/logo/20191114/c38dc69cf3fecbc1131c79f2a0ae264c52e814389fa5da52555083a866599c4d.jpg",
        "brandStageName": "未融资",
        "brandIndustry": "大数据",
        "brandScaleName": "20-99人",
        "welfareList": [
          "带薪年假",
          "通讯补贴",
          "员工旅游",
          "年终奖",
          "定期体检",
          "五险一金",
          "股票期权",
          "交通补助",
          "团体商业险",
          "餐补",
          "节日福利",
          "补充医疗保险"
        ],
        "industry": 100005,
        "contact": false,
        "showTopPosition": false
      },
      {
        "securityId": "lRLHXuAe_obfM-p1z5ZjmEHqUvKnAFHzSQTukmQcCBuk_uTOjkxeDTojSACRuPwcKlBiiLy0TODCnOa4t2MyjiDPiSu4MoXHP3j8WWCBYLKsIYeBBRZGAHXfrcBO2thVbZZZM1twC3FTi5P6zMoAsA~~",
        "bossAvatar": "https://img.bosszhipin.com/beijin/upload/avatar/20231011/607f1f3d68754fd0430e592c2d232a0653fcd47ec849b0b10dbbd49dd626600719f2f2776c142a4c_s.jpg.webp",
        "bossCert": 3,
        "encryptBossId": "1fbef51a852aeda70nx62ti0GFRR",
        "bossName": "邓女士",
        "bossTitle": "人力",
        "goldHunter": 0,
        "bossOnline": true,
        "encryptJobId": "84523cf89af75d301HB83d-9E1pQ",
        "expectId": 0,
        "jobName": "医学数据专员",
        "lid": "954vhY6j6aJ.search.162",
        "salaryDesc": "8-13K",
        "jobLabels": [
          "1-3年",
          "本科"
        ],
        "jobValidStatus": 1,
        "iconWord": "",
        "skills": [
          "临床工作经验",
          "医学相关专业",
          "医院信息系统"
        ],
        "jobExperience": "1-3年",
        "daysPerWeekDesc": "",
        "leastMonthDesc": "",
        "jobDegree": "本科",
        "cityName": "北京",
        "areaDistrict": "海淀区",
        "businessDistrict": "学院路",
        "jobType": 0,
        "proxyJob": 0,
        "proxyType": 0,
        "anonymous": 0,
        "outland": 0,
        "optimal": 0,
        "iconFlagList": [],
        "itemId": 162,
        "city": 101010100,
        "isShield": 0,
        "atsDirectPost": false,
        "gps": null,
        "encryptBrandId": "8f580ba1be2477691Xx70966",
        "brandName": "医渡科技",
        "brandLogo": "https://img.bosszhipin.com/beijin/upload/com/workfeel/20220317/7bf6f160950405e92e1bc6732b716a8bd82538e488eb524cc13743a3ae215439e8537c9563259f54.jpg",
        "brandStageName": "已上市",
        "brandIndustry": "互联网",
        "brandScaleName": "1000-9999人",
        "welfareList": [
          "商业保险",
          "定期团建",
          "团建聚餐",
          "年终奖",
          "零食下午茶",
          "餐补",
          "带薪年假",
          "股票期权",
          "节日福利",
          "生日福利",
          "五险一金",
          "补充商业保险",
          "定期体检"
        ],
        "industry": 100020,
        "contact": false,
        "showTopPosition": false
      },
      {
        "securityId": "NrrzA3kBBXGB4-H12iDhXllAREWK4PijT34RPmn7zGA-9gMfPDSdKmLutDLo-2D8x6icj2GLrDBN-hlr7GLUIIWRpdugW-FEAseMHc65PaAKTgPM3E2ssFLIh8mMjbkeTxdzoiW4JQeXrLjoCqGLZg~~",
        "bossAvatar": "https://img.bosszhipin.com/beijin/upload/tmp/20210323/5adfdc75c406d20fbfe96df2922eb63495c095c8b56cf85f09ddf735a225fc45_s.jpg",
        "bossCert": 3,
        "encryptBossId": "d10466cefc2fbc690HZz39S0GVE~",
        "bossName": "李先生",
        "bossTitle": "HRBP",
        "goldHunter": 0,
        "bossOnline": true,
        "encryptJobId": "c34b3ae5aab7a80f1Xx-29S5GVRQ",
        "expectId": 0,
        "jobName": "教务数据专员",
        "lid": "954vhY6j6aJ.search.163",
        "salaryDesc": "6-8K",
        "jobLabels": [
          "1-3年",
          "本科"
        ],
        "jobValidStatus": 1,
        "iconWord": "",
        "skills": [
          "数学/统计相关专业",
          "数据分析/挖掘经验"
        ],
        "jobExperience": "1-3年",
        "daysPerWeekDesc": "",
        "leastMonthDesc": "",
        "jobDegree": "本科",
        "cityName": "郑州",
        "areaDistrict": "金水区",
        "businessDistrict": "龙子湖校区",
        "jobType": 0,
        "proxyJob": 0,
        "proxyType": 0,
        "anonymous": 0,
        "outland": 0,
        "optimal": 0,
        "iconFlagList": [],
        "itemId": 163,
        "city": 101180100,
        "isShield": 0,
        "atsDirectPost": false,
        "gps": null,
        "encryptBrandId": "78d37a40ee3fb9150HVz39S5Ew~~",
        "brandName": "新东方",
        "brandLogo": "https://img.bosszhipin.com/beijin/mcs/banner/41792219759e470776e4f7d43f2303dacfcd208495d565ef66e7dff9f98764da.jpg",
        "brandStageName": "已上市",
        "brandIndustry": "在线教育",
        "brandScaleName": "10000人以上",
        "welfareList": [
          "员工旅游",
          "餐补",
          "节日福利",
          "五险一金",
          "年终奖",
          "带薪年假",
          "定期体检"
        ],
        "industry": 100012,
        "contact": false,
        "showTopPosition": false
      },
      {
        "securityId": "G1xCQUdrdrIiR-k1oZNR61eBW8vKE-IvWbJOSUFz_rHR3XL3zfut-lS9kGdLEZdkKqAFBtkYmwwzFcmm9rzyb-TwVtm2rCBh2gyXnKPYGmlPbakt7QE~",
        "bossAvatar": "https://img.bosszhipin.com/beijin/upload/avatar/20210729/d65504b62808a5c8ef4fe7cac0a1f795a842cff6e84608b68da25ec384762fdf_s.jpg",
        "bossCert": 3,
        "encryptBossId": "41e78e76dd27076303N90961GFA~",
        "bossName": "陈女士",
        "bossTitle": "人事经理",
        "goldHunter": 0,
        "bossOnline": false,
        "encryptJobId": "8f82f25a16a89efe1Hd-2NW5ElRQ",
        "expectId": 0,
        "jobName": "数据顾问",
        "lid": "954vhY6j6aJ.search.164",
        "salaryDesc": "7-12K",
        "jobLabels": [
          "1-3年",
          "本科"
        ],
        "jobValidStatus": 1,
        "iconWord": "",
        "skills": [
          "SQL",
          "Python",
          "计算机相关专业",
          "数据分析/挖掘经验"
        ],
        "jobExperience": "1-3年",
        "daysPerWeekDesc": "",
        "leastMonthDesc": "",
        "jobDegree": "本科",
        "cityName": "常州",
        "areaDistrict": "新北区",
        "businessDistrict": "黄山路",
        "jobType": 0,
        "proxyJob": 0,
        "proxyType": 0,
        "anonymous": 0,
        "outland": 0,
        "optimal": 0,
        "iconFlagList": [],
        "itemId": 164,
        "city": 101191100,
        "isShield": 0,
        "atsDirectPost": false,
        "gps": null,
        "encryptBrandId": "097a34c481c26cee1nRy2t-4FVA~",
        "brandName": "师创教育",
        "brandLogo": "https://img.bosszhipin.com/beijin/upload/com/workfeel/20230504/7bf6f160950405e9ef9541ea454d3025ea1dd083badfb4eeb666024ad98e1ea7b6ba6c10acabdc1d.jpg",
        "brandStageName": "未融资",
        "brandIndustry": "计算机软件",
        "brandScaleName": "20-99人",
        "welfareList": [
          "生日福利",
          "节日福利",
          "五险一金",
          "员工旅游",
          "零食下午茶",
          "团建聚餐",
          "年终奖",
          "定期体检",
          "带薪年假"
        ],
        "industry": 100021,
        "contact": false,
        "showTopPosition": false
      },
      {
        "securityId": "H66VuZ186pNTm-Y1MbRUcZW54hQY9ml8rsToIlKimMgBVamUErzStlWSZwQf4YcsWBzwAzC8lNlacuqaI6TwlSmstiMp1Kfwy-7DvV4SmaJeq7C77A~~",
        "bossAvatar": "https://img.bosszhipin.com/boss/avatar/avatar_15.png",
        "bossCert": 3,
        "encryptBossId": "64aa3fba1ed892240nF70tq9E1NY",
        "bossName": "池先生",
        "bossTitle": "部门经理",
        "goldHunter": 0,
        "bossOnline": false,
        "encryptJobId": "fe51bb2b3afe23071X192dW1ElBX",
        "expectId": 0,
        "jobName": "数据编辑",
        "lid": "954vhY6j6aJ.search.165",
        "salaryDesc": "6-9K",
        "jobLabels": [
          "经验不限",
          "本科"
        ],
        "jobValidStatus": 1,
        "iconWord": "",
        "skills": [
          "SQL",
          "Python",
          "Power BI",
          "数学/统计相关专业",
          "计算机相关专业",
          "数据分析/挖掘经验"
        ],
        "jobExperience": "经验不限",
        "daysPerWeekDesc": "",
        "leastMonthDesc": "",
        "jobDegree": "本科",
        "cityName": "北京",
        "areaDistrict": "海淀区",
        "businessDistrict": "公主坟",
        "jobType": 0,
        "proxyJob": 0,
        "proxyType": 0,
        "anonymous": 0,
        "outland": 0,
        "optimal": 0,
        "iconFlagList": [],
        "itemId": 165,
        "city": 101010100,
        "isShield": 0,
        "atsDirectPost": false,
        "gps": null,
        "encryptBrandId": "87a47143557ea8001nB_2d61",
        "brandName": "万方数据",
        "brandLogo": "https://img.bosszhipin.com/beijin/upload/com/logo/20220506/7b5b554d84f9729c79bf25042651faa2b355d9aabd33b834c60a577edf8af362c857597f6d737c1f.png",
        "brandStageName": "未融资",
        "brandIndustry": "互联网",
        "brandScaleName": "20-99人",
        "welfareList": [
          "年终奖",
          "五险一金",
          "年终奖",
          "工龄奖",
          "定期体检",
          "底薪加提成",
          "交通补助",
          "员工旅游",
          "保底工资",
          "团建聚餐",
          "节日福利",
          "补充医疗保险",
          "餐补",
          "绩效奖金",
          "意外险",
          "带薪年假",
          "住房补贴",
          "高温补贴",
          "通讯补贴",
          "生日福利"
        ],
        "industry": 100020,
        "contact": false,
        "showTopPosition": false
      },
      {
        "securityId": "ISfhWDTVuSbOh-B1Spubu-v4R2H8nzqLBXzXg-qN3zOfYgo6ZphRkESs3pXSx3oDB3d7FgLq1ZuJbssrdnsCFLi7y2fxPySP4atnaeDQUP-tmHIhFmrtLyo0AFimBI5wcBccvSIgQH3hvZAKM_i9_A~~",
        "bossAvatar": "https://img.bosszhipin.com/boss/avatar/avatar_3.png",
        "bossCert": 3,
        "encryptBossId": "9e26600c299a26e91XV53dW9ElU~",
        "bossName": "王女士",
        "bossTitle": "招聘经理",
        "goldHunter": 0,
        "bossOnline": true,
        "encryptJobId": "91c760a666c8a7f81HN73dq0E1VQ",
        "expectId": 0,
        "jobName": "初级数据产品经理",
        "lid": "954vhY6j6aJ.search.166",
        "salaryDesc": "8-12K·13薪",
        "jobLabels": [
          "1-3年",
          "本科"
        ],
        "jobValidStatus": 1,
        "iconWord": "",
        "skills": [
          "SQL",
          "Python",
          "数学/统计相关专业",
          "金融行业数据相关经验",
          "计算机相关专业",
          "mysql"
        ],
        "jobExperience": "1-3年",
        "daysPerWeekDesc": "",
        "leastMonthDesc": "",
        "jobDegree": "本科",
        "cityName": "杭州",
        "areaDistrict": "西湖区",
        "businessDistrict": "文三路",
        "jobType": 0,
        "proxyJob": 0,
        "proxyType": 0,
        "anonymous": 0,
        "outland": 0,
        "optimal": 0,
        "iconFlagList": [],
        "itemId": 166,
        "city": 101210100,
        "isShield": 0,
        "atsDirectPost": false,
        "gps": null,
        "encryptBrandId": "01a7f1821589b1ac1nFz2tq0FQ~~",
        "brandName": "源诚科技",
        "brandLogo": "https://img.bosszhipin.com/beijin/mcs/chatphoto/20180312/9047daeaf9d0eb8ebed15c125ffa9cb110329b0fb233e636a527b7e094ee15b4.jpg",
        "brandStageName": "未融资",
        "brandIndustry": "计算机软件",
        "brandScaleName": "100-499人",
        "welfareList": [
          "加班补助",
          "定期体检",
          "有无线网",
          "住房补贴",
          "节日福利",
          "股票期权",
          "保底工资",
          "年终奖",
          "补充医疗保险",
          "带薪年假",
          "意外险",
          "五险一金",
          "零食下午茶",
          "生日福利",
          "团建聚餐",
          "员工旅游"
        ],
        "industry": 100021,
        "contact": false,
        "showTopPosition": false
      },
      {
        "securityId": "rIOGrjan4SK32-21E7r5eqJcqw1vW2L5rbt1xQ6Zb7SIG0TGhRENdV26Uh8aVDupgNqhOGRk9qzO0xnQhDyhFBE17L00IqS0tJ919dD9ZPRp9xc~",
        "bossAvatar": "https://img.bosszhipin.com/beijin/mcs/useravatar/20170627/ab3f1cc3d564a14b3e11d4c79dd69eb930edb7252d0b7e90d37d8dc0c920eb83_s.jpg",
        "bossCert": 3,
        "encryptBossId": "7bb7c8b8f3125c831XR-3du9F1A~",
        "bossName": "王女士",
        "bossTitle": "HRM",
        "goldHunter": 0,
        "bossOnline": false,
        "encryptJobId": "2a5adaac9b702aeb1nd629m1E1U~",
        "expectId": 0,
        "jobName": "数据处理员",
        "lid": "954vhY6j6aJ.search.167",
        "salaryDesc": "3-6K",
        "jobLabels": [
          "经验不限",
          "大专"
        ],
        "jobValidStatus": 1,
        "iconWord": "",
        "skills": [
          "SQLServer",
          "数据处理",
          "数据库"
        ],
        "jobExperience": "经验不限",
        "daysPerWeekDesc": "",
        "leastMonthDesc": "",
        "jobDegree": "大专",
        "cityName": "南京",
        "areaDistrict": "浦口区",
        "businessDistrict": "泰山",
        "jobType": 0,
        "proxyJob": 0,
        "proxyType": 0,
        "anonymous": 0,
        "outland": 0,
        "optimal": 0,
        "iconFlagList": [],
        "itemId": 167,
        "city": 101190100,
        "isShield": 0,
        "atsDirectPost": false,
        "gps": null,
        "encryptBrandId": "958d8bc5c5ae6ad90HN629y-",
        "brandName": "舒克资产",
        "brandLogo": "https://img.bosszhipin.com/beijin/mcs/chatphoto/20170627/79c790a02b2ff981bb948c22432531b077f3d9f54ce7f3756442d56ebcb68c8a.jpg",
        "brandStageName": "B轮",
        "brandIndustry": "互联网金融",
        "brandScaleName": "20-99人",
        "welfareList": [
          "年终奖",
          "补充公积金",
          "五险一金",
          "股票期权",
          "定期体检"
        ],
        "industry": 100206,
        "contact": false,
        "showTopPosition": false
      },
      {
        "securityId": "2laQ9DYx5GcHy-S1zCPO97009Kcsnbt_LTnUYnvUL75sL-Gt0QR1WwMhhw-xhdc2IxcTCe85L03uMzkIWJdw-kE-uoHnO-9w26ujBHMXxO5bE0RHqlQNIUKw99yhbzO8AX9nTmqX7EmBTiBYMlxdpQ~~",
        "bossAvatar": "https://img.bosszhipin.com/beijin/upload/tmp/20210427/445f196a1b4bc1dc78fb63aa32049f2314f27f19a7be6d1b8f221d63f69df8fb_s.jpg",
        "bossCert": 3,
        "encryptBossId": "d9ae5be0445c11343nN82Nm0EFM~",
        "bossName": "高女士",
        "bossTitle": "招聘",
        "goldHunter": 0,
        "bossOnline": true,
        "encryptJobId": "1942d95f43a16f431HV829y4E1NQ",
        "expectId": 0,
        "jobName": "鲜力达招聘数据专员",
        "lid": "954vhY6j6aJ.search.168",
        "salaryDesc": "5-6K",
        "jobLabels": [
          "1-3年",
          "大专"
        ],
        "jobValidStatus": 1,
        "iconWord": "",
        "skills": [
          "PowerQuery",
          "VBA",
          "BI"
        ],
        "jobExperience": "1-3年",
        "daysPerWeekDesc": "",
        "leastMonthDesc": "",
        "jobDegree": "大专",
        "cityName": "无锡",
        "areaDistrict": "滨湖区",
        "businessDistrict": "蠡湖",
        "jobType": 0,
        "proxyJob": 0,
        "proxyType": 0,
        "anonymous": 0,
        "outland": 0,
        "optimal": 0,
        "iconFlagList": [],
        "itemId": 168,
        "city": 101190200,
        "isShield": 0,
        "atsDirectPost": false,
        "gps": null,
        "encryptBrandId": "476e27ac310ab3d80XZz0tW0Eg~~",
        "brandName": "维果多农产品贸易",
        "brandLogo": "https://img.bosszhipin.com/beijin/app/mobile/normal-0e3f1e4441a21d4874cece3a3d81f0fe.png",
        "brandStageName": "未融资",
        "brandIndustry": "批发/零售",
        "brandScaleName": "1000-9999人",
        "welfareList": [
          "团建聚餐",
          "免费工装",
          "工龄奖",
          "餐补",
          "保底工资",
          "节日福利",
          "加班补助",
          "带薪年假",
          "年终奖",
          "全勤奖",
          "生日福利",
          "五险一金",
          "包吃",
          "有无线网",
          "节假日加班费"
        ],
        "industry": 100503,
        "contact": false,
        "showTopPosition": false
      },
      {
        "securityId": "NoGHFSAU2Hz8Z-I1nrN4GkRg1-ES6J_p1G5pxSmJrsVT8OokG3K_G-L8qPr60YOFB2rXUbcATL5EB-x23D9eIlKVim0HjHQC1knwUT2AMWDHs3ks6ow~",
        "bossAvatar": "https://img.bosszhipin.com/beijin/upload/avatar/20240718/607f1f3d68754fd09556c2564841a761b07464e6c8f67286f21db3506c4be9e93e3bf37dc39aeffc_s.jpg.webp",
        "bossCert": 3,
        "encryptBossId": "0503c2922966ae730nR82ty5ElM~",
        "bossName": "翟女士",
        "bossTitle": "HR",
        "goldHunter": 0,
        "bossOnline": false,
        "encryptJobId": "337d49a108018d371HJ_39i1FlZU",
        "expectId": 0,
        "jobName": "电商数据专员",
        "lid": "954vhY6j6aJ.search.169",
        "salaryDesc": "4-7K",
        "jobLabels": [
          "1-3年",
          "大专"
        ],
        "jobValidStatus": 1,
        "iconWord": "",
        "skills": [
          "熟练使用Excel",
          "熟练使用office软件",
          "沟通表达能力好"
        ],
        "jobExperience": "1-3年",
        "daysPerWeekDesc": "",
        "leastMonthDesc": "",
        "jobDegree": "大专",
        "cityName": "惠州",
        "areaDistrict": "惠城区",
        "businessDistrict": "下角",
        "jobType": 0,
        "proxyJob": 0,
        "proxyType": 0,
        "anonymous": 0,
        "outland": 0,
        "optimal": 0,
        "iconFlagList": [],
        "itemId": 169,
        "city": 101280300,
        "isShield": 0,
        "atsDirectPost": false,
        "gps": null,
        "encryptBrandId": "78f65e58516e54f71nFy2du0ElI~",
        "brandName": "爱华仕箱包集团",
        "brandLogo": "https://img.bosszhipin.com/beijin/upload/com/logo/20230303/7b5b554d84f9729c45d06345720e23c83882c22c70e84ba485b68c112ce4bd4457cc04293c261a31.jpg",
        "brandStageName": "未融资",
        "brandIndustry": "批发/零售",
        "brandScaleName": "500-999人",
        "welfareList": [
          "公费学历提升",
          "五险一金",
          "节日福利",
          "员工关怀",
          "餐补",
          "员工旅游",
          "入职周年关怀",
          "绩效奖金",
          "生日福利",
          "带薪假期"
        ],
        "industry": 100503,
        "contact": false,
        "showTopPosition": false
      },
      {
        "securityId": "FCVEzMXaukQlU-w1BssNB-NTkiUnPB57Udyy-KH3XIyqbBgEcSv3PD24q4TFTEYS0XAYfsyhWSt1HumTmfLXfVfMFiXNQASXZqjrqhri-775FZzlhj4a",
        "bossAvatar": "https://img.bosszhipin.com/beijin/upload/avatar/20230625/607f1f3d68754fd0d3bf8f79877040bfbbd923b0571678af1239ba39741f65285c3fa02ba9611c6d_s.png",
        "bossCert": 3,
        "encryptBossId": "474329450c493d6e0XR_09y8GFVS",
        "bossName": "罗先生",
        "bossTitle": "招聘者",
        "goldHunter": 0,
        "bossOnline": false,
        "encryptJobId": "b1821071346b57091HJ72dq9EFdX",
        "expectId": 0,
        "jobName": "金融数据专员",
        "lid": "954vhY6j6aJ.search.170",
        "salaryDesc": "6-11K",
        "jobLabels": [
          "1-3年",
          "大专"
        ],
        "jobValidStatus": 1,
        "iconWord": "",
        "skills": [
          "数学/统计相关专业",
          "金融行业数据相关经验",
          "风控相关经验"
        ],
        "jobExperience": "1-3年",
        "daysPerWeekDesc": "",
        "leastMonthDesc": "",
        "jobDegree": "大专",
        "cityName": "上海",
        "areaDistrict": "闵行区",
        "businessDistrict": "莘庄",
        "jobType": 0,
        "proxyJob": 0,
        "proxyType": 0,
        "anonymous": 0,
        "outland": 0,
        "optimal": 0,
        "iconFlagList": [],
        "itemId": 170,
        "city": 101020100,
        "isShield": 0,
        "atsDirectPost": false,
        "gps": null,
        "encryptBrandId": "12c8f7a535ee50151Xx629S6FVo~",
        "brandName": "上海星旦商务咨询",
        "brandLogo": "https://img.bosszhipin.com/beijin/icon/894ce6fa7e58d64d57e7f22d2f3a9d18afa7fcceaa24b8ea28f56f1bb14732c0.png",
        "brandStageName": "",
        "brandIndustry": "投资/融资",
        "brandScaleName": "20-99人",
        "welfareList": [
          "五险一金",
          "底薪加提成",
          "年终奖",
          "绩效奖金",
          "保底工资",
          "带薪年假"
        ],
        "industry": 100207,
        "contact": false,
        "showTopPosition": false
      },
      {
        "securityId": "Ng_9cX7C65uyW-b1zcGDaJMWCO_HjEAa6iLdvS-MZuqU98uijjZl3RDwYF-ITB-5n_sDkMAQgY_CKoyLFloGUdHxsWLUatEkzpBfHCAFQQTT2o3RPLY~",
        "bossAvatar": "https://img.bosszhipin.com/beijin/upload/avatar/20210420/53d9da55c4bb4dd59bba89ed544f0a830ead9c5e74b8ffa947203d6d57fde68e_s.png",
        "bossCert": 3,
        "encryptBossId": "b78bf5a624e23a2b0nRz29q-F1tS",
        "bossName": "赖女士",
        "bossTitle": "HR",
        "goldHunter": 0,
        "bossOnline": false,
        "encryptJobId": "2784ad72ec1d17671HNz3tW6F1FX",
        "expectId": 0,
        "jobName": "数据管理（DM）",
        "lid": "954vhY6j6aJ.search.171",
        "salaryDesc": "9-13K·13薪",
        "jobLabels": [
          "1-3年",
          "本科"
        ],
        "jobValidStatus": 1,
        "iconWord": "",
        "skills": [
          "数据管理",
          "SAS",
          "R语言",
          "医药相关专业",
          "SPSS",
          "统计学相关专业",
          "医学相关专业",
          "临床试验"
        ],
        "jobExperience": "1-3年",
        "daysPerWeekDesc": "",
        "leastMonthDesc": "",
        "jobDegree": "本科",
        "cityName": "南京",
        "areaDistrict": "雨花台区",
        "businessDistrict": "南京南站",
        "jobType": 0,
        "proxyJob": 0,
        "proxyType": 0,
        "anonymous": 0,
        "outland": 0,
        "optimal": 0,
        "iconFlagList": [],
        "itemId": 171,
        "city": 101190100,
        "isShield": 0,
        "atsDirectPost": false,
        "gps": null,
        "encryptBrandId": "abd39e7951253ce01XB63t2-Eg~~",
        "brandName": "南京从一医药科技...",
        "brandLogo": "https://img.bosszhipin.com/beijin/mcs/chatphoto/20180726/f9b5c7fbb35e479e9b600c58890e4954cfcd208495d565ef66e7dff9f98764da.jpg",
        "brandStageName": "不需要融资",
        "brandIndustry": "医疗服务",
        "brandScaleName": "100-499人",
        "welfareList": [
          "团建聚餐",
          "零食下午茶",
          "通讯补贴",
          "交通补助",
          "节日福利",
          "意外险",
          "员工旅游",
          "股票期权",
          "带薪年假",
          "定期体检",
          "年终奖",
          "餐补",
          "生日福利",
          "补充医疗保险",
          "五险一金"
        ],
        "industry": 100402,
        "contact": false,
        "showTopPosition": false
      },
      {
        "securityId": "slZOlfTqE6RbF-F1Peb34Jc3TlDwKkN29Wq50hHHlyHfUhjLmrORwAQqYxPUCl71HKdUcuR-P-jh2JQ2JHGjVl4MmRWBsnF14C2Eyt3246B77OvIgkTo",
        "bossAvatar": "https://img.bosszhipin.com/boss/avatar/avatar_6.png",
        "bossCert": 3,
        "encryptBossId": "10e8001f12106f7f0nZ639q9GVVT",
        "bossName": "杨先生",
        "bossTitle": "运营总监",
        "goldHunter": 0,
        "bossOnline": false,
        "encryptJobId": "c50cfac884d5f2fd1HV_092_FFdX",
        "expectId": 0,
        "jobName": "Power BI数据可视化工程师",
        "lid": "954vhY6j6aJ.search.172",
        "salaryDesc": "5-7K",
        "jobLabels": [
          "经验不限",
          "本科"
        ],
        "jobValidStatus": 1,
        "iconWord": "",
        "skills": [
          "Power BI"
        ],
        "jobExperience": "经验不限",
        "daysPerWeekDesc": "",
        "leastMonthDesc": "",
        "jobDegree": "本科",
        "cityName": "深圳",
        "areaDistrict": "南山区",
        "businessDistrict": "科技园",
        "jobType": 0,
        "proxyJob": 0,
        "proxyType": 0,
        "anonymous": 0,
        "outland": 0,
        "optimal": 0,
        "iconFlagList": [],
        "itemId": 172,
        "city": 101280600,
        "isShield": 0,
        "atsDirectPost": false,
        "gps": null,
        "encryptBrandId": "21343516bb01846c1nB_3tm0GVc~",
        "brandName": "悦策科技",
        "brandLogo": "https://img.bosszhipin.com/beijin/upload/com/workfeel/20210720/adb9fb9468dbfd9fc7d02e426d9f26a36e984e40739874dca9f5a16a9a917e51.jpg",
        "brandStageName": "未融资",
        "brandIndustry": "大数据",
        "brandScaleName": "20-99人",
        "welfareList": [
          "零食下午茶",
          "年终奖",
          "节日福利",
          "五险一金",
          "带薪年假",
          "员工旅游",
          "餐补",
          "定期体检",
          "股票期权"
        ],
        "industry": 100005,
        "contact": false,
        "showTopPosition": false
      },
      {
        "securityId": "vO4EUnCJgYiAx-m1Z56bEcK2qOtqAnK6RHgUV8yNYxqqjFQtoe2r_gWSQcXYX2uJh1KP32ox7qVaBtDg1RDGLmFIioUE1BFGDRchFlzYJ6FtkZz7P6ib",
        "bossAvatar": "https://img.bosszhipin.com/beijin/upload/avatar/20200810/b31412feeaa131126fca006e46e06a3e355614da75c9d8a2154fa74c8beeec4d_s.jpg",
        "bossCert": 3,
        "encryptBossId": "8e80f02a6eead6841nV809S-EFpT",
        "bossName": "赵女士",
        "bossTitle": "部门经理",
        "goldHunter": 0,
        "bossOnline": false,
        "encryptJobId": "512aeda848c373111HR72tm8E1pT",
        "expectId": 0,
        "jobName": "数据挖掘工程师",
        "lid": "954vhY6j6aJ.search.173",
        "salaryDesc": "7-11K·13薪",
        "jobLabels": [
          "1-3年",
          "本科"
        ],
        "jobValidStatus": 1,
        "iconWord": "",
        "skills": [
          "机器学习建模经验",
          "数据分析/挖掘经验",
          "SQL",
          "Python",
          "数学/统计相关专业"
        ],
        "jobExperience": "1-3年",
        "daysPerWeekDesc": "",
        "leastMonthDesc": "",
        "jobDegree": "本科",
        "cityName": "兰州",
        "areaDistrict": "安宁区",
        "businessDistrict": "北滨河路",
        "jobType": 0,
        "proxyJob": 0,
        "proxyType": 0,
        "anonymous": 0,
        "outland": 0,
        "optimal": 0,
        "iconFlagList": [],
        "itemId": 173,
        "city": 101160100,
        "isShield": 0,
        "atsDirectPost": false,
        "gps": null,
        "encryptBrandId": "15d6dbac195727231XN62t28GFI~",
        "brandName": "中海华晟",
        "brandLogo": "https://img.bosszhipin.com/beijin/upload/com/workfeel/20230613/7bf6f160950405e91c0c642d1381a6af00c3aff2d67381c3296ba611ef96c39a017dcefa8eb9cc81.png",
        "brandStageName": "不需要融资",
        "brandIndustry": "运营商/增值服务",
        "brandScaleName": "100-499人",
        "welfareList": [
          "餐补",
          "生日福利",
          "节日福利",
          "带薪年假",
          "定期体检",
          "年终奖",
          "节假日加班费",
          "通讯补贴",
          "交通补助",
          "加班补助",
          "五险一金"
        ],
        "industry": 100025,
        "contact": false,
        "showTopPosition": false
      },
      {
        "securityId": "FPf9dB_d5MzTJ-u1vol2-wJJgbT3uy5N2UknxujfY4Y6n5lhX8CN61zcDCkv4nSs09o--foJaM33DL4XvfwVje0juTQ0VZXKjt-i1LrBrGvQYO8fZpM~",
        "bossAvatar": "https://img.bosszhipin.com/boss/avatar/avatar_1.png",
        "bossCert": 3,
        "encryptBossId": "9e281c4b24f1a89c0nR-3N65FlBS",
        "bossName": "邢女士",
        "bossTitle": "人力资源",
        "goldHunter": 0,
        "bossOnline": false,
        "encryptJobId": "22f71ec30b2493841nRy2d25FFZQ",
        "expectId": 0,
        "jobName": "气象数据工程师",
        "lid": "954vhY6j6aJ.search.174",
        "salaryDesc": "6-10K",
        "jobLabels": [
          "经验不限",
          "本科"
        ],
        "jobValidStatus": 1,
        "iconWord": "",
        "skills": [
          "气象",
          "数据"
        ],
        "jobExperience": "经验不限",
        "daysPerWeekDesc": "",
        "leastMonthDesc": "",
        "jobDegree": "本科",
        "cityName": "上海",
        "areaDistrict": "",
        "businessDistrict": "",
        "jobType": 0,
        "proxyJob": 0,
        "proxyType": 0,
        "anonymous": 0,
        "outland": 0,
        "optimal": 0,
        "iconFlagList": [],
        "itemId": 174,
        "city": 101020100,
        "isShield": 0,
        "atsDirectPost": false,
        "gps": null,
        "encryptBrandId": "1544d6a9da142aa01n1-0tm-EA~~",
        "brandName": "培谊科技",
        "brandLogo": "https://c-res.zhipin.com/jrs/d75ba0f8089b63f3efcd2b4cc909490f.jpg",
        "brandStageName": "未融资",
        "brandIndustry": "计算机服务",
        "brandScaleName": "20-99人",
        "welfareList": [
          "交通补助",
          "保底工资",
          "五险一金",
          "通讯补贴",
          "绩效奖金",
          "加班补助",
          "夜班补助",
          "定期体检",
          "团建聚餐",
          "年终奖",
          "餐补"
        ],
        "industry": 100023,
        "contact": false,
        "showTopPosition": false
      },
      {
        "securityId": "-yW7EuPIi9RVU-e14iHWu9_v9ADuovJu4JBpTm0SgJ5ul3_5kUyuWSov5R5hJWByi3fn3zsFRjcNnT8r8Mmt5qv6oaW3yyFgL9Ik6OwzukLtpblUkdaFGXRgk8v2MSXsWdImwKNR5x0jQw_FPhV2Rp92",
        "bossAvatar": "https://img.bosszhipin.com/beijin/upload/avatar/20211130/607f1f3d68754fd06669ccbab09493b124e2be4349dc286954dea3e9673c8ee4bd0767c35186149e_s.jpg",
        "bossCert": 3,
        "encryptBossId": "dda7966fd5c1381f0nZ62Nq-EVdQ",
        "bossName": "黄女士",
        "bossTitle": "人事经理HRM",
        "goldHunter": 0,
        "bossOnline": true,
        "encryptJobId": "e9607ecdb0482dd01XF73dq5FlNX",
        "expectId": 0,
        "jobName": "临床数据管理员",
        "lid": "954vhY6j6aJ.search.175",
        "salaryDesc": "6-11K",
        "jobLabels": [
          "1-3年",
          "本科"
        ],
        "jobValidStatus": 1,
        "iconWord": "",
        "skills": [
          "医学相关专业",
          "医药相关专业",
          "统计学相关专业",
          "SAS"
        ],
        "jobExperience": "1-3年",
        "daysPerWeekDesc": "",
        "leastMonthDesc": "",
        "jobDegree": "本科",
        "cityName": "武汉",
        "areaDistrict": "江汉区",
        "businessDistrict": "建设大道",
        "jobType": 0,
        "proxyJob": 0,
        "proxyType": 0,
        "anonymous": 0,
        "outland": 0,
        "optimal": 0,
        "iconFlagList": [],
        "itemId": 175,
        "city": 101200100,
        "isShield": 0,
        "atsDirectPost": false,
        "gps": null,
        "encryptBrandId": "3ee6c41f00eca03d1XZz3t29GVo~",
        "brandName": "武汉知止医药科技",
        "brandLogo": "https://c-res.zhipin.com/jrs/4_3df5d94cfffb5fc20c4f1fe957c7a2ca.jpg",
        "brandStageName": "",
        "brandIndustry": "生物/制药",
        "brandScaleName": "20-99人",
        "welfareList": [
          "零食下午茶",
          "底薪加提成",
          "团建聚餐",
          "全勤奖",
          "交通补助",
          "五险一金",
          "带薪年假",
          "住房补贴",
          "定期体检",
          "节日福利",
          "年终奖",
          "意外险",
          "员工旅游",
          "餐补",
          "绩效奖金",
          "生日福利",
          "通讯补贴"
        ],
        "industry": 100401,
        "contact": false,
        "showTopPosition": false
      },
      {
        "securityId": "3Mpyzr3lE3oQx-d11qoQZ1wEIizxp3p6mhmHCJPLqiiexzAKqLbVGiz3yLsZ0Z2ZAsPmiioykoQKVQMOnQyv8ZofBmr4bIi9QrdE-rYFQroPxuzMRa0~",
        "bossAvatar": "https://img.bosszhipin.com/beijin/upload/avatar/20230214/607f1f3d68754fd0e03857ab67827c140975e3b95d0cac17fd2b6391ffb611d4fa249339a20c36c1_s.jpg",
        "bossCert": 3,
        "encryptBossId": "4fb837b30f7b4c2f0nRz0tW4GFVV",
        "bossName": "刘女士",
        "bossTitle": "人事经理",
        "goldHunter": 0,
        "bossOnline": false,
        "encryptJobId": "9e0217fa6ab3097b1Hd-0ti7GVNQ",
        "expectId": 0,
        "jobName": "导航数据员",
        "lid": "954vhY6j6aJ.search.176",
        "salaryDesc": "3-6K",
        "jobLabels": [
          "在校/应届",
          "大专"
        ],
        "jobValidStatus": 1,
        "iconWord": "",
        "skills": [
          "机器学习建模经验",
          "计算机相关专业"
        ],
        "jobExperience": "在校/应届",
        "daysPerWeekDesc": "",
        "leastMonthDesc": "",
        "jobDegree": "大专",
        "cityName": "石家庄",
        "areaDistrict": "桥西区",
        "businessDistrict": "新石北路",
        "jobType": 5,
        "proxyJob": 0,
        "proxyType": 0,
        "anonymous": 0,
        "outland": 0,
        "optimal": 0,
        "iconFlagList": [],
        "itemId": 176,
        "city": 101090100,
        "isShield": 0,
        "atsDirectPost": false,
        "gps": null,
        "encryptBrandId": "ee74c5c6b56ea4cf0H1z3d2_EQ~~",
        "brandName": "河北天测",
        "brandLogo": "https://img.bosszhipin.com/beijin/mcs/chatphoto/20200912/7b89209cf0f08f3bd3958b9ae3d590a7c72f7ae00e79d936da8ae7ff6084fd47_s.jpg",
        "brandStageName": "不需要融资",
        "brandIndustry": "大数据",
        "brandScaleName": "100-499人",
        "welfareList": [
          "全勤奖",
          "年终奖",
          "员工旅游",
          "餐补",
          "节日福利"
        ],
        "industry": 100005,
        "contact": false,
        "showTopPosition": false
      },
      {
        "securityId": "Q5il3P2BxuYZD--1gmfkzEuzh3Z33-C8J62ziusdpA6kCDkHXs0cWysyHiFNqmPGR-0wQH9uheoDOF-ZDVdXykmR4-pJfEUIxUefOq4-3Vh7dkC50wPGh21-rkkGFJn3nmnqRyUAEQKGsMEDqwAbJVM~",
        "bossAvatar": "https://img.bosszhipin.com/boss/avatar/avatar_1.png",
        "bossCert": 3,
        "encryptBossId": "400381b1cd78c2560HF629y7EFM~",
        "bossName": "和女士",
        "bossTitle": "HR",
        "goldHunter": 0,
        "bossOnline": true,
        "encryptJobId": "82da6f5987ca93d31HN70tu5EltR",
        "expectId": 0,
        "jobName": "临床数据管理员",
        "lid": "954vhY6j6aJ.search.177",
        "salaryDesc": "6-7K",
        "jobLabels": [
          "1-3年",
          "本科"
        ],
        "jobValidStatus": 1,
        "iconWord": "",
        "skills": [
          "临床工作经验",
          "医药相关专业",
          "统计学相关专业"
        ],
        "jobExperience": "1-3年",
        "daysPerWeekDesc": "",
        "leastMonthDesc": "",
        "jobDegree": "本科",
        "cityName": "郑州",
        "areaDistrict": "金水区",
        "businessDistrict": "省电视台",
        "jobType": 0,
        "proxyJob": 0,
        "proxyType": 0,
        "anonymous": 0,
        "outland": 0,
        "optimal": 0,
        "iconFlagList": [],
        "itemId": 177,
        "city": 101180100,
        "isShield": 0,
        "atsDirectPost": false,
        "gps": null,
        "encryptBrandId": "85deb2e85208a8201nB62Nm-FlI~",
        "brandName": "临研通",
        "brandLogo": "https://img.bosszhipin.com/beijin/upload/com/workfeel/20210524/62b1feb19b8a00c0bc540fd7d223467f74d56c93f1feaa2b0d8497450c14fd2e.jpg",
        "brandStageName": "天使轮",
        "brandIndustry": "医疗服务",
        "brandScaleName": "100-499人",
        "welfareList": [
          "五险一金",
          "补充医疗保险",
          "带薪年假",
          "节日福利"
        ],
        "industry": 100402,
        "contact": false,
        "showTopPosition": false
      },
      {
        "securityId": "sCcTR1Ldaizno-91SN5HXBkruoxMqIsX3tUhErhH1zzJR89Dg2geMOu-TIS8iVdVyzbqwqgT5km7hZ7kOLPOLxg11ucib_TeppJ6AwAfD_RfqwC-QZM~",
        "bossAvatar": "https://img.bosszhipin.com/beijin/upload/avatar/20200406/2b1fe380ce3fa703cfb810cbd3ffafda0550bb0d646e11734c6603b0fd453701_s.png",
        "bossCert": 3,
        "encryptBossId": "6967cbe1f18e4e1c1nR43t-_FlFW",
        "bossName": "陆女士",
        "bossTitle": "人事",
        "goldHunter": 0,
        "bossOnline": false,
        "encryptJobId": "b0332639a763ac861X1839q8FFBQ",
        "expectId": 0,
        "jobName": "无人机数据内业处理专员",
        "lid": "954vhY6j6aJ.search.178",
        "salaryDesc": "4-8K",
        "jobLabels": [
          "1-3年",
          "大专"
        ],
        "jobValidStatus": 1,
        "iconWord": "",
        "skills": [
          "无人机",
          "无人机电力巡检",
          "无人机内业人员"
        ],
        "jobExperience": "1-3年",
        "daysPerWeekDesc": "",
        "leastMonthDesc": "",
        "jobDegree": "大专",
        "cityName": "合肥",
        "areaDistrict": "包河区",
        "businessDistrict": "罍街",
        "jobType": 0,
        "proxyJob": 0,
        "proxyType": 0,
        "anonymous": 0,
        "outland": 0,
        "optimal": 0,
        "iconFlagList": [],
        "itemId": 178,
        "city": 101220100,
        "isShield": 0,
        "atsDirectPost": false,
        "gps": null,
        "encryptBrandId": "29bcc7c55598080c03B63NS_FQ~~",
        "brandName": "西格玛电力运检",
        "brandLogo": "https://img.bosszhipin.com/beijin/upload/com/logo/20230209/7b5b554d84f9729cde0dc4c9bacb99583f2d3ebe7f95bc430550bb0d646e11734c6603b0fd453701.png",
        "brandStageName": "不需要融资",
        "brandIndustry": "其他行业",
        "brandScaleName": "20-99人",
        "welfareList": [
          "员工旅游",
          "团建聚餐",
          "年终奖",
          "五险",
          "加班补助",
          "节日福利",
          "定期体检",
          "带薪年假",
          "绩效奖金"
        ],
        "industry": 101304,
        "contact": false,
        "showTopPosition": false
      },
      {
        "securityId": "R1uIIX6TloHEs-L1eKECZAvGvxiU-xsLOM9IWFDGr3wWle828dOHfHwROjXsiwAN_KCTio9J4-MZ4ibefwQJX89nZQ_sLAmn1dyYzoqeSVHktF1G",
        "bossAvatar": "https://img.bosszhipin.com/beijin/upload/avatar/20231121/607f1f3d68754fd0a82a52f83ac3d391b5b53c712ec339f873302487ec9099bcb025036e49fe8b69_s.jpg.webp",
        "bossCert": 3,
        "encryptBossId": "c762af7ed3b8eff41nZ-3Nm7EVtU",
        "bossName": "邓先生",
        "bossTitle": "HR",
        "goldHunter": 0,
        "bossOnline": false,
        "encryptJobId": "de35e27829b928031Hdy3tW-GFBT",
        "expectId": 0,
        "jobName": "数据录入（可接受实习生）",
        "lid": "954vhY6j6aJ.search.179",
        "salaryDesc": "5-7K·14薪",
        "jobLabels": [
          "经验不限",
          "本科"
        ],
        "jobValidStatus": 1,
        "iconWord": "",
        "skills": [
          "经济/工商管理相关专业",
          "金融行业数据相关经验",
          "计算机相关专业"
        ],
        "jobExperience": "经验不限",
        "daysPerWeekDesc": "",
        "leastMonthDesc": "",
        "jobDegree": "本科",
        "cityName": "杭州",
        "areaDistrict": "余杭区",
        "businessDistrict": "五常",
        "jobType": 0,
        "proxyJob": 0,
        "proxyType": 0,
        "anonymous": 0,
        "outland": 0,
        "optimal": 0,
        "iconFlagList": [],
        "itemId": 179,
        "city": 101210100,
        "isShield": 0,
        "atsDirectPost": false,
        "gps": null,
        "encryptBrandId": "6e919732311f4d0b1HBy2N8~",
        "brandName": "同花顺",
        "brandLogo": "https://img.bosszhipin.com/beijin/upload/com/logo/20190930/4202dd7f280a60ba6312f4954397c9ad44d02158167cec33f073ab7fb4bb5bee.jpg",
        "brandStageName": "已上市",
        "brandIndustry": "互联网",
        "brandScaleName": "1000-9999人",
        "welfareList": [
          "定期体检",
          "节日福利",
          "零食下午茶",
          "股票期权",
          "交通补助",
          "免费班车",
          "包吃",
          "带薪年假",
          "五险一金",
          "年终奖"
        ],
        "industry": 100020,
        "contact": false,
        "showTopPosition": false
      },
      {
        "securityId": "BYWa9Wpzmm1Pn-y12zPmyGKEKq0aq5Eu33xasaCvNWj2v6mQqmCJYRWqjfI8MB5UqdonFmAyPyYTP9dkPUN7GbRfq9lxkUwM2FZH-i9YmFOl5ur6Jlf4Oq_K0cAaMinr644TKpfeo_InoaziaK6nar0~",
        "bossAvatar": "https://img.bosszhipin.com/beijin/upload/avatar/20210729/6d5111b251ae0cdba1f1ca4c66718f1ee56aa6c0c125c750c16b3812b174c610_s.jpg",
        "bossCert": 3,
        "encryptBossId": "05fc8fcba3073ed11Xx43t6_GVI~",
        "bossName": "李女士",
        "bossTitle": "人事主管",
        "goldHunter": 0,
        "bossOnline": true,
        "encryptJobId": "41bdbba2488b312d1Xx43N-0EFdS",
        "expectId": 0,
        "jobName": "汽车数据适配工程师",
        "lid": "954vhY6j6aJ.search.180",
        "salaryDesc": "6-9K",
        "jobLabels": [
          "1-3年",
          "大专"
        ],
        "jobValidStatus": 1,
        "iconWord": "",
        "skills": [
          "汽车后市场"
        ],
        "jobExperience": "1-3年",
        "daysPerWeekDesc": "",
        "leastMonthDesc": "",
        "jobDegree": "大专",
        "cityName": "武汉",
        "areaDistrict": "东西湖区",
        "businessDistrict": "吴家山",
        "jobType": 0,
        "proxyJob": 0,
        "proxyType": 0,
        "anonymous": 0,
        "outland": 0,
        "optimal": 0,
        "iconFlagList": [],
        "itemId": 180,
        "city": 101200100,
        "isShield": 0,
        "atsDirectPost": false,
        "gps": null,
        "encryptBrandId": "f756f943616f23461n1y3Nm8EFU~",
        "brandName": "智配库",
        "brandLogo": "https://img.bosszhipin.com/beijin/upload/com/workfeel/20211218/7bf6f160950405e925c17d3c1c040961f19de718695c32dcdec7a353cc051610623d98cc4df61384.jpg",
        "brandStageName": "未融资",
        "brandIndustry": "汽车后市场",
        "brandScaleName": "100-499人",
        "welfareList": [],
        "industry": 100807,
        "contact": false,
        "showTopPosition": false
      }
    ],
    "totalCount": 300,
    "brandCard": null
  }
}